src/delta-lake-trello-qxf2/generate_results.py
src/delta-lake-trello-qxf2/config/__init__.py
src/delta-lake-trello-qxf2/config/delta_table_conf.py
src/delta-lake-trello-qxf2/config/skype_conf.py
src/delta-lake-trello-qxf2/config/trello_conf.py
src/delta-lake-trello-qxf2/helpers/__init__.py
src/delta-lake-trello-qxf2/helpers/common_functions.py
src/delta-lake-trello-qxf2/helpers/get_boards.py
src/delta-lake-trello-qxf2/helpers/skype_sender.py
src/delta-lake-trello-qxf2/helpers/spark_helper.py
src/delta-lake-trello-qxf2/helpers/trello_functions.py
src/delta-lake-trello-qxf2/jobs/__init__.py
src/delta-lake-trello-qxf2/jobs/example_script.py
src/delta-lake-trello-qxf2/jobs/get_unique_cards_silver.py
src/delta-lake-trello-qxf2/jobs/ingest_cards_bronze.py
src/delta-lake-trello-qxf2/jobs/ingest_cards_bronze_historical.py
src/delta-lake-trello-qxf2/jobs/ingest_members_bronze.py
src/delta-lake-trello-qxf2/jobs/noactivity_cards_gold.py
src/delta-lake-trello-qxf2/jobs/refine_current_doing_cards_silver.py
src/delta-lake-trello-qxf2/jobs/refine_historical_current_doing_cards_silver.py
src/delta-lake-trello-qxf2/jobs/sravanti_cards_gold.py
src/delta-lake-trello-qxf2/operations/__init__.py
src/delta-lake-trello-qxf2/operations/bronze_layer_operations.py
src/delta-lake-trello-qxf2/operations/silver_layer_operations.py
delta_lake_trello_qxf2-0.0.1.dist-info/METADATA
delta_lake_trello_qxf2-0.0.1.dist-info/WHEEL
delta_lake_trello_qxf2-0.0.1.dist-info/licenses/LICENSE
delta_lake_trello_qxf2-0.0.1.dist-info/RECORD
