Metadata-Version: 2.1
Name: delta-lake-trello-qxf2
Version: 0.0.1
Summary: Delta Lake implementation for Trello, Qxf2
Project-URL: Homepage, https://github.com/qxf2/delta-lake-trello
Author-email: Sravanti Tatiraju <sravanti.tatiraju@qxf2.com>
License-File: LICENSE
Classifier: License :: OSI Approved :: MIT License
Classifier: Operating System :: OS Independent
Classifier: Programming Language :: Python :: 3
Requires-Python: >=3.7
